odoo9_addon_mail_debrand-9.0.1.0.0-py2.7-nspkg.pth
odoo_addons/mail_debrand/__openerp__.py
odoo_addons/mail_debrand/__init__.py
odoo_addons/mail_debrand/README.rst
odoo_addons/mail_debrand/i18n/it.po
odoo_addons/mail_debrand/i18n/es.po
odoo_addons/mail_debrand/i18n/sl.po
odoo_addons/mail_debrand/i18n/fr.po
odoo_addons/mail_debrand/i18n/el_GR.po
odoo_addons/mail_debrand/i18n/fi.po
odoo_addons/mail_debrand/data/mail_data.xml
odoo_addons/mail_debrand/static/description/icon.png
odoo9_addon_mail_debrand-9.0.1.0.0.dist-info/top_level.txt
odoo9_addon_mail_debrand-9.0.1.0.0.dist-info/WHEEL
odoo9_addon_mail_debrand-9.0.1.0.0.dist-info/RECORD
odoo9_addon_mail_debrand-9.0.1.0.0.dist-info/metadata.json
odoo9_addon_mail_debrand-9.0.1.0.0.dist-info/DESCRIPTION.rst
odoo9_addon_mail_debrand-9.0.1.0.0.dist-info/METADATA
odoo9_addon_mail_debrand-9.0.1.0.0.dist-info/namespace_packages.txt
